sucuri/__init__.py
sucuri/files.py
sucuri/rendering.py
sucuri-0.2.6.dist-info/AUTHORS
sucuri-0.2.6.dist-info/LICENSE.txt
sucuri-0.2.6.dist-info/METADATA
sucuri-0.2.6.dist-info/WHEEL
sucuri-0.2.6.dist-info/top_level.txt
sucuri-0.2.6.dist-info/RECORD
