Metadata-Version: 2.1
Name: sucuri
Version: 0.2.6
Summary: Simple and efficient Template Engine for Python projects
Home-page: https://github.com/marcosstefani/sucuri
Author: Marcos Rosa
Author-email: marcos.cantor@gmail.com
License: UNKNOWN
Keywords: template engine python
Platform: UNKNOWN
Classifier: Development Status :: 3 - Alpha
Classifier: Intended Audience :: Developers
Classifier: Topic :: Software Development :: Build Tools
Classifier: License :: OSI Approved :: BSD License
Requires-Python: >=3
